{
  "id": "mandarin-tangerine",
  "name": "温州蜜柑",
  "classification": {
    "科": "芸香科",
    "属": "柑橘属",
    "别名": [
      "无核蜜橘",
      "温州柑"
    ],
    "类型": "经典柑橘类水果"
  },
  "origin_range": [
    "浙江省",
    "湖南省",
    "湖北省"
  ],
  "best_season": "10-12 月（深秋初冬，果肉细嫩，甜酸适口）",
  "nutrition_per_100g": {
    "热量": "50kcal",
    "碳水化合物": "12.2g",
    "蛋白质": "0.8g",
    "维生素 C": "31mg",
    "膳食纤维": "1.8g"
  },
  "benefits": [
    "增强免疫力，预防感冒",
    "促进胶原蛋白合成",
    "改善皮肤状态"
  ],
  "tips": [
    "无核或少核，食用方便",
    "果皮可晒干作陈皮",
    "避免空腹大量食用"
  ]
}