{
  "id": "wo-gan",
  "name": "沃柑",
  "classification": {
    "科": "芸香科",
    "属": "柑橘属",
    "别名": [
      "沃桔",
      "杂交柑"
    ],
    "类型": "柑橘类水果"
  },
  "origin_range": [
    "广西壮族自治区",
    "云南省",
    "重庆市"
  ],
  "best_season": "12-4 月（冬春季节，果肉脆嫩化渣，高糖低酸）",
  "nutrition_per_100g": {
    "热量": "52kcal",
    "碳水化合物": "13.0g",
    "蛋白质": "0.8g",
    "维生素 C": "30mg",
    "膳食纤维": "1.7g"
  },
  "benefits": [
    "补充冬季维 C 需求",
    "促进肠道蠕动",
    "增强皮肤弹性"
  ],
  "tips": [
    "果皮易剥，可直接手剥食用",
    "冷藏后口感更佳",
    "糖尿病患者适量食用"
  ]
}